psdr/__init__.py
psdr/basis.py
psdr/coord.py
psdr/cvxopt_kkt_ex.py
psdr/duu.py
psdr/exceptions.py
psdr/function.py
psdr/gn.py
psdr/gp.py
psdr/initialization.py
psdr/lipschitz.py
psdr/lipschitz_partial.py
psdr/lipschitz_utils.py
psdr/local_linear.py
psdr/minimax.py
psdr/misc.py
psdr/nonlin.py
psdr/opg.py
psdr/pgf.py
psdr/poly.py
psdr/polyridge.py
psdr/quadrature.py
psdr/ridge.py
psdr/seqlp.py
psdr/subspace.py
psdr/vandermonde.py
psdr/demos/__init__.py
psdr/demos/_multif_domains3d.py
psdr/demos/_multif_linear_constraints.py
psdr/demos/beam.py
psdr/demos/borehole.py
psdr/demos/golinski.py
psdr/demos/hartmann.py
psdr/demos/multif.py
psdr/demos/naca0012.py
psdr/demos/oas.py
psdr/demos/otl_circuit.py
psdr/demos/piston.py
psdr/demos/polynomial.py
psdr/demos/robot_arm.py
psdr/demos/wing_weight.py
psdr/domains/__init__.py
psdr/domains/box.py
psdr/domains/convexhull.py
psdr/domains/domain.py
psdr/domains/euclidean.py
psdr/domains/linineq.py
psdr/domains/linquad.py
psdr/domains/lognormal.py
psdr/domains/normal.py
psdr/domains/point.py
psdr/domains/random.py
psdr/domains/tensor.py
psdr/domains/unbounded.py
psdr/domains/uniform.py
psdr/geometry/__init__.py
psdr/geometry/cdist.py
psdr/geometry/fill.py
psdr/geometry/geometry.py
psdr/geometry/miniball.py
psdr/geometry/vertex.py
psdr/sample/__init__.py
psdr/sample/initial.py
psdr/sample/latin.py
psdr/sample/maximin.py
psdr/sample/maximin_coffeehouse.py
psdr/sample/minimax.py
psdr/sample/minimax_lloyd.py
psdr/sample/minimax_scale.py
psdr/sample/poisson.py
psdr/sample/projection.py
psdr/sample/random_sample.py
psdr/sample/sample.py
psdr/sample/seqmaximin.py
psdr/sample/sobol.py
psdr/sample/util.py
psdr-0.3.5.dist-info/LICENSE
psdr-0.3.5.dist-info/METADATA
psdr-0.3.5.dist-info/WHEEL
psdr-0.3.5.dist-info/top_level.txt
psdr-0.3.5.dist-info/RECORD
